src/__init__.py
src/__main__.py
src/main/__init__.py
src/main/__main__.py
src/main/python/Emotion_Detection2.py
src/main/python/Processing.py
src/main/python/__init__.py
src/main/python/__main__.py
src/main/python/background.py
src/main/python/main.py
BackgroundVellore-1.0.2.dist-info/METADATA
BackgroundVellore-1.0.2.dist-info/WHEEL
BackgroundVellore-1.0.2.dist-info/entry_points.txt
BackgroundVellore-1.0.2.dist-info/top_level.txt
BackgroundVellore-1.0.2.dist-info/RECORD
